{
    "author": "Piotr Maciejewski",
    "bpp": 16,
    "events": {
        "PLAY": {
            "frames": [
                {
                    "check": [
                        208,
                        189,
                        85
                    ],
                    "filename": "1_krzak3_0.png",
                    "name": "SET_1",
                    "position_x": 0,
                    "position_y": 0
                },
                {
                    "check": [
                        208,
                        189,
                        85
                    ],
                    "filename": "1_krzak3_0.png",
                    "name": "SET_1",
                    "position_x": 0,
                    "position_y": 0
                },
                {
                    "check": [
                        208,
                        189,
                        85
                    ],
                    "filename": "1_krzak3_0.png",
                    "name": "SET_1",
                    "position_x": 0,
                    "position_y": 0
                },
                {
                    "check": [
                        208,
                        189,
                        85
                    ],
                    "filename": "1_krzak3_0.png",
                    "name": "SET_1",
                    "position_x": -2,
                    "position_y": 0
                },
                {
                    "check": [
                        208,
                        189,
                        85
                    ],
                    "filename": "1_krzak3_0.png",
                    "name": "SET_1",
                    "position_x": -6,
                    "position_y": 0
                },
                {
                    "check": [
                        208,
                        189,
                        85
                    ],
                    "filename": "1_krzak3_0.png",
                    "name": "SET_1",
                    "position_x": -12,
                    "position_y": 0
                },
                {
                    "check": [
                        208,
                        189,
                        85
                    ],
                    "filename": "1_krzak3_0.png",
                    "name": "SET_1",
                    "position_x": -21,
                    "position_y": 0
                },
                {
                    "check": [
                        208,
                        189,
                        85
                    ],
                    "filename": "1_krzak3_0.png",
                    "name": "SET_1",
                    "position_x": -34,
                    "position_y": 0
                },
                {
                    "check": [
                        208,
                        189,
                        85
                    ],
                    "filename": "1_krzak3_0.png",
                    "name": "SET_1",
                    "position_x": -50,
                    "position_y": 0
                },
                {
                    "check": [
                        208,
                        189,
                        85
                    ],
                    "filename": "1_krzak3_0.png",
                    "name": "SET_1",
                    "position_x": -72,
                    "position_y": 0
                },
                {
                    "check": [
                        208,
                        189,
                        85
                    ],
                    "filename": "1_krzak3_0.png",
                    "name": "SET_1",
                    "position_x": -99,
                    "position_y": 0
                },
                {
                    "check": [
                        208,
                        189,
                        85
                    ],
                    "filename": "1_krzak3_0.png",
                    "name": "SET_1",
                    "position_x": -132,
                    "position_y": 0
                },
                {
                    "check": [
                        208,
                        189,
                        85
                    ],
                    "filename": "1_krzak3_0.png",
                    "name": "SET_1",
                    "position_x": -171,
                    "position_y": 0
                },
                {
                    "check": [
                        208,
                        189,
                        85
                    ],
                    "filename": "1_krzak3_0.png",
                    "name": "SET_1",
                    "position_x": -218,
                    "position_y": 0
                },
                {
                    "check": [
                        208,
                        189,
                        85
                    ],
                    "filename": "1_krzak3_0.png",
                    "name": "SET_1",
                    "position_x": -273,
                    "position_y": 0
                },
                {
                    "check": [
                        208,
                        189,
                        85
                    ],
                    "filename": "1_krzak3_0.png",
                    "name": "SET_1",
                    "position_x": -335,
                    "position_y": 0
                },
                {
                    "check": [
                        208,
                        189,
                        85
                    ],
                    "filename": "1_krzak3_0.png",
                    "name": "SET_1",
                    "position_x": -407,
                    "position_y": 0
                },
                {
                    "check": [
                        208,
                        189,
                        85
                    ],
                    "filename": "1_krzak3_0.png",
                    "name": "SET_1",
                    "position_x": -488,
                    "position_y": 0
                },
                {
                    "check": [
                        208,
                        189,
                        85
                    ],
                    "filename": "1_krzak3_0.png",
                    "name": "SET_1",
                    "position_x": -580,
                    "position_y": 0
                },
                {
                    "check": [
                        208,
                        189,
                        85
                    ],
                    "filename": "1_krzak3_0.png",
                    "name": "SET_1",
                    "position_x": -682,
                    "position_y": 0
                },
                {
                    "check": [
                        208,
                        189,
                        85
                    ],
                    "filename": "1_krzak3_0.png",
                    "name": "SET_1",
                    "position_x": -796,
                    "position_y": -1
                }
            ],
            "loop": 0,
            "transparency": 255
        }
    },
    "images": {
        "1_krzak3_0.png": {
            "compression": 3,
            "name": "SET_1"
        }
    },
    "transparency": 255
}